toscript/__init__.py
toscript/to.py
toscript-0.1.data/scripts/toscript-python
toscript-0.1.dist-info/DESCRIPTION.rst
toscript-0.1.dist-info/METADATA
toscript-0.1.dist-info/RECORD
toscript-0.1.dist-info/WHEEL
toscript-0.1.dist-info/metadata.json
toscript-0.1.dist-info/top_level.txt
