Metadata-Version: 2.0
Name: toscript
Version: 0.1
Summary: Helps with setting up envs quickly
Home-page: https://github.com/tklijnsma/toscript.git
Author: Thomas Klijnsma
Author-email: thomasklijnsma@gmail.com
License: UNKNOWN
Platform: UNKNOWN
